svc_tools.py
svc_tools/__init__.py
svc_tools/decorators.py
svc_tools/loggers.py
svc_tools-0.1.0.dist-info/DESCRIPTION.rst
svc_tools-0.1.0.dist-info/METADATA
svc_tools-0.1.0.dist-info/RECORD
svc_tools-0.1.0.dist-info/WHEEL
svc_tools-0.1.0.dist-info/metadata.json
svc_tools-0.1.0.dist-info/top_level.txt
