Metadata-Version: 2.0
Name: svc-tools
Version: 0.1.0
Summary: Tools to aide in the development of microservice applications.
Home-page: https://github.com/tylerwince/svc-tools
Author: Tyler Wince
Author-email: tyler@myndshft.com
License: MIT
Platform: UNKNOWN
Classifier: License :: OSI Approved :: MIT License
Classifier: Programming Language :: Python
Classifier: Programming Language :: Python :: 3 :: Only
Classifier: Programming Language :: Python :: 3
Classifier: Programming Language :: Python :: 3.3
Classifier: Programming Language :: Python :: 3.4
Classifier: Programming Language :: Python :: 3.5
Classifier: Programming Language :: Python :: 3.6
Classifier: Topic :: Software Development :: Libraries :: Python Modules
Requires-Dist: python-json-logger
